KNRscore/KNRscore.py
KNRscore/__init__.py
KNRscore/examples.py
knrscore-2.0.0.dist-info/licenses/LICENSE
knrscore-2.0.0.dist-info/METADATA
knrscore-2.0.0.dist-info/WHEEL
knrscore-2.0.0.dist-info/top_level.txt
knrscore-2.0.0.dist-info/RECORD
