Metadata-Version: 2.4
Name: KNRscore
Version: 2.0.0
Summary: KNRScore is a Python package for computing K-Nearest-Rank Similarity, a metric that quantifies local structural similarity between two maps or embeddings.
Author-email: Erdogan Taskesen <erdogant@gmail.com>
License: MIT License
Project-URL: Homepage, https://erdogant.github.io/KNRscore
Project-URL: Download, https://github.com/erdogant/KNRscore/archive/{version}.tar.gz
Keywords: Python,tsne,UMAP,comparison
Classifier: Programming Language :: Python :: 3
Classifier: License :: OSI Approved :: MIT License
Classifier: Operating System :: OS Independent
Requires-Python: >=3
License-File: LICENSE
Requires-Dist: matplotlib
Requires-Dist: numpy
Requires-Dist: tqdm
Requires-Dist: scipy
Requires-Dist: imagesc
Requires-Dist: scatterd
Requires-Dist: requests
Dynamic: license-file
